{
    "name": "string",
    "includedFiles": "all",
    "externalFlashFiles": [],
    "top": "nano9k",
    "constraintsFile": "constraints.cst",
    "programMode": "ram",
    "testBenches": [
        "../../testbenches/alu_tb.v",
        "../../testbenches/cpu_tb.v",
        "../../testbenches/fetch_decode_tb.v",
        "../../testbenches/fetch_tb.v", 
        "../../testbenches/if_de_ex_tb.v",
        "../../testbenches/if_de_ex_wb_tb.v",
        "../../testbenches/instruction_tb.v",
        "../../testbenches/memory_tb.v",
        "../../testbenches/ram_tb.v",
        "../../testbenches/rom_tb.v", 
        "../../testbenches/writeback_tb.v"
    ],
    "nextPnrGowinOptions": ["--top", "nano9k"],
    "synthGowinOptions": [],
    "baudRate": 115200,
    "board": "tangnano9k",
    "skipCstChecking": false
}